pybadges/__init__.py
pybadges/__main__.py
pybadges/badge-template-full.svg
pybadges/default-widths.json
pybadges/pil_text_measurer.py
pybadges/precalculate_text.py
pybadges/precalculated_text_measurer.py
pybadges/py.typed
pybadges/text_measurer.py
pybadges/trend.py
pybadges/version.py
pybadges_trend-1.0.0.dist-info/LICENSE
pybadges_trend-1.0.0.dist-info/METADATA
pybadges_trend-1.0.0.dist-info/WHEEL
pybadges_trend-1.0.0.dist-info/top_level.txt
pybadges_trend-1.0.0.dist-info/RECORD
