Metadata-Version: 2.1
Name: pybadges-trend
Version: 1.0.0
Summary: A library and command-line tool for generating Github-style badges
Home-page: https://github.com/rahul-deepsource/pybadges-trend
Author: Rahul Jha
Author-email: rj722@protonmail.com
License: Apache-2.0
Keywords: github gh-badges badge shield status
Platform: UNKNOWN
Classifier: Development Status :: 5 - Production/Stable
Classifier: Intended Audience :: Developers
Classifier: Intended Audience :: Developers
Classifier: License :: OSI Approved :: Apache Software License
Classifier: Programming Language :: Python
Classifier: Programming Language :: Python :: 3
Classifier: Programming Language :: Python :: 3.4
Classifier: Programming Language :: Python :: 3.5
Classifier: Programming Language :: Python :: 3.6
Classifier: Programming Language :: Python :: 3.7
Classifier: Operating System :: OS Independent
Requires-Python: >=3.4
Requires-Dist: Jinja2 (<3,>=2.9.0)
Requires-Dist: requests (<3,>=2.9.0)
Provides-Extra: dev
Requires-Dist: fonttools (>=3.26) ; extra == 'dev'
Requires-Dist: nox ; extra == 'dev'
Requires-Dist: Pillow (>=5) ; extra == 'dev'
Requires-Dist: pytest (>=3.6) ; extra == 'dev'
Requires-Dist: xmldiff (>=2.4) ; extra == 'dev'
Provides-Extra: pil-measurement
Requires-Dist: Pillow (<6,>=5) ; extra == 'pil-measurement'
Provides-Extra: trend
Requires-Dist: drawsvg (>=1.6.0) ; extra == 'trend'
Requires-Dist: numpy (>=1.19.0) ; extra == 'trend'
